[{
  "_id": {
    "$oid": "68e3d42eeea279769bcebede"
  },
  "user_id": {
    "$oid": "671b00000000000000000102"
  },
  "type": "like",
  "message": "Nishant liked your post.",
  "is_read": false,
  "created_at": {
    "$date": "2025-10-06T14:35:00.000Z"
  }
},
{
  "_id": {
    "$oid": "68e3d42eeea279769bcebedf"
  },
  "user_id": {
    "$oid": "671b00000000000000000101"
  },
  "type": "comment",
  "message": "Khushi commented on your MongoDB post.",
  "is_read": true,
  "created_at": {
    "$date": "2025-10-06T14:36:00.000Z"
  }
},
{
  "_id": {
    "$oid": "68e3d42eeea279769bcebee0"
  },
  "user_id": {
    "$oid": "671b00000000000000000104"
  },
  "type": "follow",
  "message": "Rohan started following you.",
  "is_read": false,
  "created_at": {
    "$date": "2025-10-06T14:37:00.000Z"
  }
},
{
  "_id": {
    "$oid": "68e3d42eeea279769bcebee1"
  },
  "user_id": {
    "$oid": "671b00000000000000000105"
  },
  "type": "message",
  "message": "Karan replied to your message.",
  "is_read": true,
  "created_at": {
    "$date": "2025-10-06T14:38:00.000Z"
  }
},
{
  "_id": {
    "$oid": "68e3d42eeea279769bcebee2"
  },
  "user_id": {
    "$oid": "671b00000000000000000108"
  },
  "type": "comment",
  "message": "Arnav commented on your cricket post.",
  "is_read": false,
  "created_at": {
    "$date": "2025-10-06T14:39:00.000Z"
  }
},
{
  "_id": {
    "$oid": "68e3d42eeea279769bcebee3"
  },
  "user_id": {
    "$oid": "671b00000000000000000107"
  },
  "type": "like",
  "message": "Siddharth liked your study vlog post.",
  "is_read": true,
  "created_at": {
    "$date": "2025-10-06T14:40:00.000Z"
  }
},
{
  "_id": {
    "$oid": "68e3d42eeea279769bcebee4"
  },
  "user_id": {
    "$oid": "671b00000000000000000103"
  },
  "type": "message",
  "message": "Arnav sent you trek photos.",
  "is_read": true,
  "created_at": {
    "$date": "2025-10-06T14:41:00.000Z"
  }
},
{
  "_id": {
    "$oid": "68e4cb05215da4a4cccec3e2"
  },
  "user_id": {
    "$oid": "671b00000000000000000107"
  },
  "type": "comment",
  "from_user": {
    "$oid": "671b00000000000000000101"
  },
  "post_id": {
    "$oid": "68e4c90d215da4a4cccec3ba"
  },
  "read": false,
  "created_at": {
    "$date": "2025-10-07T08:10:45.319Z"
  }
},
{
  "_id": {
    "$oid": "68e4cb05215da4a4cccec3e3"
  },
  "user_id": {
    "$oid": "671b00000000000000000103"
  },
  "type": "comment",
  "from_user": {
    "$oid": "671b00000000000000000102"
  },
  "post_id": {
    "$oid": "68e4c90d215da4a4cccec39e"
  },
  "read": false,
  "created_at": {
    "$date": "2025-10-07T08:10:45.341Z"
  }
},
{
  "_id": {
    "$oid": "68e4cb05215da4a4cccec3e4"
  },
  "user_id": {
    "$oid": "671b00000000000000000103"
  },
  "type": "mention",
  "from_user": {
    "$oid": "671b00000000000000000102"
  },
  "post_id": {
    "$oid": "68e4c90c215da4a4cccec390"
  },
  "read": true,
  "created_at": {
    "$date": "2025-10-07T08:10:45.355Z"
  }
},
{
  "_id": {
    "$oid": "68e4cb05215da4a4cccec3e5"
  },
  "user_id": {
    "$oid": "671b00000000000000000101"
  },
  "type": "follow",
  "from_user": {
    "$oid": "671b00000000000000000105"
  },
  "post_id": null,
  "read": false,
  "created_at": {
    "$date": "2025-10-07T08:10:45.358Z"
  }
},
{
  "_id": {
    "$oid": "68e4cb05215da4a4cccec3e6"
  },
  "user_id": {
    "$oid": "671b00000000000000000103"
  },
  "type": "like",
  "from_user": {
    "$oid": "671b00000000000000000107"
  },
  "post_id": {
    "$oid": "68e4c90d215da4a4cccec3b3"
  },
  "read": false,
  "created_at": {
    "$date": "2025-10-07T08:10:45.370Z"
  }
},
{
  "_id": {
    "$oid": "68e4cb05215da4a4cccec3e7"
  },
  "user_id": {
    "$oid": "671b00000000000000000106"
  },
  "type": "comment",
  "from_user": {
    "$oid": "671b00000000000000000107"
  },
  "post_id": {
    "$oid": "68e4c90c215da4a4cccec376"
  },
  "read": true,
  "created_at": {
    "$date": "2025-10-07T08:10:45.378Z"
  }
},
{
  "_id": {
    "$oid": "68e4cb05215da4a4cccec3e8"
  },
  "user_id": {
    "$oid": "671b00000000000000000102"
  },
  "type": "like",
  "from_user": {
    "$oid": "671b00000000000000000105"
  },
  "post_id": {
    "$oid": "68e4c90d215da4a4cccec3d1"
  },
  "read": false,
  "created_at": {
    "$date": "2025-10-07T08:10:45.386Z"
  }
},
{
  "_id": {
    "$oid": "68e4cb05215da4a4cccec3e9"
  },
  "user_id": {
    "$oid": "671b00000000000000000107"
  },
  "type": "like",
  "from_user": {
    "$oid": "671b00000000000000000108"
  },
  "post_id": {
    "$oid": "68e4c90d215da4a4cccec3c8"
  },
  "read": true,
  "created_at": {
    "$date": "2025-10-07T08:10:45.393Z"
  }
},
{
  "_id": {
    "$oid": "68e4cb05215da4a4cccec3ea"
  },
  "user_id": {
    "$oid": "671b00000000000000000104"
  },
  "type": "like",
  "from_user": {
    "$oid": "671b00000000000000000102"
  },
  "post_id": {
    "$oid": "68e4c90c215da4a4cccec36b"
  },
  "read": false,
  "created_at": {
    "$date": "2025-10-07T08:10:45.400Z"
  }
},
{
  "_id": {
    "$oid": "68e4cb05215da4a4cccec3eb"
  },
  "user_id": {
    "$oid": "671b00000000000000000103"
  },
  "type": "mention",
  "from_user": {
    "$oid": "671b00000000000000000101"
  },
  "post_id": {
    "$oid": "68e4c90c215da4a4cccec370"
  },
  "read": false,
  "created_at": {
    "$date": "2025-10-07T08:10:45.407Z"
  }
},
{
  "_id": {
    "$oid": "68e4cb05215da4a4cccec3ec"
  },
  "user_id": {
    "$oid": "671b00000000000000000105"
  },
  "type": "like",
  "from_user": {
    "$oid": "671b00000000000000000104"
  },
  "post_id": {
    "$oid": "68e4c90d215da4a4cccec3bd"
  },
  "read": false,
  "created_at": {
    "$date": "2025-10-07T08:10:45.415Z"
  }
},
{
  "_id": {
    "$oid": "68e4cb05215da4a4cccec3ed"
  },
  "user_id": {
    "$oid": "671b00000000000000000106"
  },
  "type": "like",
  "from_user": {
    "$oid": "671b00000000000000000107"
  },
  "post_id": {
    "$oid": "68e4c90d215da4a4cccec3ca"
  },
  "read": true,
  "created_at": {
    "$date": "2025-10-07T08:10:45.422Z"
  }
},
{
  "_id": {
    "$oid": "68e4cb05215da4a4cccec3ee"
  },
  "user_id": {
    "$oid": "671b00000000000000000106"
  },
  "type": "mention",
  "from_user": {
    "$oid": "671b00000000000000000102"
  },
  "post_id": {
    "$oid": "68e4c90d215da4a4cccec3b4"
  },
  "read": true,
  "created_at": {
    "$date": "2025-10-07T08:10:45.431Z"
  }
},
{
  "_id": {
    "$oid": "68e4cb05215da4a4cccec3ef"
  },
  "user_id": {
    "$oid": "671b00000000000000000103"
  },
  "type": "comment",
  "from_user": {
    "$oid": "671b00000000000000000108"
  },
  "post_id": {
    "$oid": "68e4c90d215da4a4cccec3c2"
  },
  "read": false,
  "created_at": {
    "$date": "2025-10-07T08:10:45.448Z"
  }
},
{
  "_id": {
    "$oid": "68e4cb05215da4a4cccec3f0"
  },
  "user_id": {
    "$oid": "671b00000000000000000108"
  },
  "type": "comment",
  "from_user": {
    "$oid": "671b00000000000000000102"
  },
  "post_id": {
    "$oid": "68e4c90c215da4a4cccec36d"
  },
  "read": true,
  "created_at": {
    "$date": "2025-10-07T08:10:45.456Z"
  }
},
{
  "_id": {
    "$oid": "68e4cb05215da4a4cccec3f1"
  },
  "user_id": {
    "$oid": "671b00000000000000000107"
  },
  "type": "follow",
  "from_user": {
    "$oid": "671b00000000000000000102"
  },
  "post_id": null,
  "read": false,
  "created_at": {
    "$date": "2025-10-07T08:10:45.458Z"
  }
},
{
  "_id": {
    "$oid": "68e4cb05215da4a4cccec3f2"
  },
  "user_id": {
    "$oid": "671b00000000000000000107"
  },
  "type": "follow",
  "from_user": {
    "$oid": "671b00000000000000000104"
  },
  "post_id": null,
  "read": true,
  "created_at": {
    "$date": "2025-10-07T08:10:45.459Z"
  }
},
{
  "_id": {
    "$oid": "68e4cb05215da4a4cccec3f3"
  },
  "user_id": {
    "$oid": "671b00000000000000000103"
  },
  "type": "comment",
  "from_user": {
    "$oid": "671b00000000000000000101"
  },
  "post_id": {
    "$oid": "68e4c90d215da4a4cccec39e"
  },
  "read": false,
  "created_at": {
    "$date": "2025-10-07T08:10:45.465Z"
  }
},
{
  "_id": {
    "$oid": "68e4cb05215da4a4cccec3f4"
  },
  "user_id": {
    "$oid": "671b00000000000000000105"
  },
  "type": "like",
  "from_user": {
    "$oid": "671b00000000000000000101"
  },
  "post_id": {
    "$oid": "68e4c90d215da4a4cccec3a5"
  },
  "read": false,
  "created_at": {
    "$date": "2025-10-07T08:10:45.472Z"
  }
},
{
  "_id": {
    "$oid": "68e4cb05215da4a4cccec3f5"
  },
  "user_id": {
    "$oid": "671b00000000000000000107"
  },
  "type": "like",
  "from_user": {
    "$oid": "671b00000000000000000101"
  },
  "post_id": {
    "$oid": "68e4c90c215da4a4cccec357"
  },
  "read": false,
  "created_at": {
    "$date": "2025-10-07T08:10:45.480Z"
  }
},
{
  "_id": {
    "$oid": "68e4cb05215da4a4cccec3f6"
  },
  "user_id": {
    "$oid": "671b00000000000000000108"
  },
  "type": "follow",
  "from_user": {
    "$oid": "671b00000000000000000107"
  },
  "post_id": null,
  "read": false,
  "created_at": {
    "$date": "2025-10-07T08:10:45.481Z"
  }
},
{
  "_id": {
    "$oid": "68e4cb05215da4a4cccec3f7"
  },
  "user_id": {
    "$oid": "671b00000000000000000108"
  },
  "type": "comment",
  "from_user": {
    "$oid": "671b00000000000000000107"
  },
  "post_id": {
    "$oid": "68e4c90d215da4a4cccec39f"
  },
  "read": false,
  "created_at": {
    "$date": "2025-10-07T08:10:45.491Z"
  }
},
{
  "_id": {
    "$oid": "68e4cb05215da4a4cccec3f8"
  },
  "user_id": {
    "$oid": "671b00000000000000000103"
  },
  "type": "follow",
  "from_user": {
    "$oid": "671b00000000000000000107"
  },
  "post_id": null,
  "read": false,
  "created_at": {
    "$date": "2025-10-07T08:10:45.493Z"
  }
},
{
  "_id": {
    "$oid": "68e4cb05215da4a4cccec3f9"
  },
  "user_id": {
    "$oid": "671b00000000000000000105"
  },
  "type": "like",
  "from_user": {
    "$oid": "671b00000000000000000102"
  },
  "post_id": {
    "$oid": "68e4c90d215da4a4cccec3a3"
  },
  "read": false,
  "created_at": {
    "$date": "2025-10-07T08:10:45.499Z"
  }
},
{
  "_id": {
    "$oid": "68e4cb05215da4a4cccec3fa"
  },
  "user_id": {
    "$oid": "671b00000000000000000102"
  },
  "type": "comment",
  "from_user": {
    "$oid": "671b00000000000000000106"
  },
  "post_id": {
    "$oid": "68e4c90c215da4a4cccec350"
  },
  "read": true,
  "created_at": {
    "$date": "2025-10-07T08:10:45.506Z"
  }
},
{
  "_id": {
    "$oid": "68e4cb05215da4a4cccec3fb"
  },
  "user_id": {
    "$oid": "671b00000000000000000101"
  },
  "type": "like",
  "from_user": {
    "$oid": "671b00000000000000000106"
  },
  "post_id": {
    "$oid": "68e4c90d215da4a4cccec3df"
  },
  "read": false,
  "created_at": {
    "$date": "2025-10-07T08:10:45.513Z"
  }
},
{
  "_id": {
    "$oid": "68e4cb05215da4a4cccec3fc"
  },
  "user_id": {
    "$oid": "671b00000000000000000102"
  },
  "type": "comment",
  "from_user": {
    "$oid": "671b00000000000000000103"
  },
  "post_id": {
    "$oid": "68e4c90c215da4a4cccec38b"
  },
  "read": false,
  "created_at": {
    "$date": "2025-10-07T08:10:45.523Z"
  }
},
{
  "_id": {
    "$oid": "68e4cb05215da4a4cccec3fd"
  },
  "user_id": {
    "$oid": "671b00000000000000000106"
  },
  "type": "like",
  "from_user": {
    "$oid": "671b00000000000000000104"
  },
  "post_id": {
    "$oid": "68e4c90c215da4a4cccec37a"
  },
  "read": true,
  "created_at": {
    "$date": "2025-10-07T08:10:45.529Z"
  }
},
{
  "_id": {
    "$oid": "68e4cb05215da4a4cccec3fe"
  },
  "user_id": {
    "$oid": "671b00000000000000000106"
  },
  "type": "like",
  "from_user": {
    "$oid": "671b00000000000000000105"
  },
  "post_id": {
    "$oid": "68e4c90c215da4a4cccec34e"
  },
  "read": false,
  "created_at": {
    "$date": "2025-10-07T08:10:45.536Z"
  }
},
{
  "_id": {
    "$oid": "68e4cb05215da4a4cccec3ff"
  },
  "user_id": {
    "$oid": "671b00000000000000000104"
  },
  "type": "follow",
  "from_user": {
    "$oid": "671b00000000000000000105"
  },
  "post_id": null,
  "read": true,
  "created_at": {
    "$date": "2025-10-07T08:10:45.538Z"
  }
},
{
  "_id": {
    "$oid": "68e4cb05215da4a4cccec400"
  },
  "user_id": {
    "$oid": "671b00000000000000000101"
  },
  "type": "comment",
  "from_user": {
    "$oid": "671b00000000000000000105"
  },
  "post_id": {
    "$oid": "68e4c90d215da4a4cccec3a3"
  },
  "read": true,
  "created_at": {
    "$date": "2025-10-07T08:10:45.544Z"
  }
},
{
  "_id": {
    "$oid": "68e4cb05215da4a4cccec401"
  },
  "user_id": {
    "$oid": "671b00000000000000000101"
  },
  "type": "like",
  "from_user": {
    "$oid": "671b00000000000000000107"
  },
  "post_id": {
    "$oid": "68e4c90c215da4a4cccec359"
  },
  "read": true,
  "created_at": {
    "$date": "2025-10-07T08:10:45.551Z"
  }
},
{
  "_id": {
    "$oid": "68e4cb05215da4a4cccec402"
  },
  "user_id": {
    "$oid": "671b00000000000000000101"
  },
  "type": "comment",
  "from_user": {
    "$oid": "671b00000000000000000105"
  },
  "post_id": {
    "$oid": "68e4c90d215da4a4cccec3db"
  },
  "read": false,
  "created_at": {
    "$date": "2025-10-07T08:10:45.558Z"
  }
},
{
  "_id": {
    "$oid": "68e4cb05215da4a4cccec403"
  },
  "user_id": {
    "$oid": "671b00000000000000000103"
  },
  "type": "like",
  "from_user": {
    "$oid": "671b00000000000000000107"
  },
  "post_id": {
    "$oid": "68e4c90c215da4a4cccec37b"
  },
  "read": false,
  "created_at": {
    "$date": "2025-10-07T08:10:45.564Z"
  }
},
{
  "_id": {
    "$oid": "68e4cb05215da4a4cccec404"
  },
  "user_id": {
    "$oid": "671b00000000000000000103"
  },
  "type": "like",
  "from_user": {
    "$oid": "671b00000000000000000108"
  },
  "post_id": {
    "$oid": "68e4c90c215da4a4cccec36a"
  },
  "read": false,
  "created_at": {
    "$date": "2025-10-07T08:10:45.571Z"
  }
},
{
  "_id": {
    "$oid": "68e4cb05215da4a4cccec405"
  },
  "user_id": {
    "$oid": "671b00000000000000000108"
  },
  "type": "like",
  "from_user": {
    "$oid": "671b00000000000000000107"
  },
  "post_id": {
    "$oid": "68e4c90c215da4a4cccec38d"
  },
  "read": true,
  "created_at": {
    "$date": "2025-10-07T08:10:45.577Z"
  }
},
{
  "_id": {
    "$oid": "68e4cb05215da4a4cccec406"
  },
  "user_id": {
    "$oid": "671b00000000000000000106"
  },
  "type": "like",
  "from_user": {
    "$oid": "671b00000000000000000102"
  },
  "post_id": {
    "$oid": "68e4c90d215da4a4cccec3c0"
  },
  "read": true,
  "created_at": {
    "$date": "2025-10-07T08:10:45.586Z"
  }
},
{
  "_id": {
    "$oid": "68e4cb05215da4a4cccec407"
  },
  "user_id": {
    "$oid": "671b00000000000000000103"
  },
  "type": "mention",
  "from_user": {
    "$oid": "671b00000000000000000107"
  },
  "post_id": {
    "$oid": "68e4c90d215da4a4cccec3db"
  },
  "read": true,
  "created_at": {
    "$date": "2025-10-07T08:10:45.593Z"
  }
},
{
  "_id": {
    "$oid": "68e4cb05215da4a4cccec408"
  },
  "user_id": {
    "$oid": "671b00000000000000000103"
  },
  "type": "follow",
  "from_user": {
    "$oid": "671b00000000000000000101"
  },
  "post_id": null,
  "read": false,
  "created_at": {
    "$date": "2025-10-07T08:10:45.595Z"
  }
},
{
  "_id": {
    "$oid": "68e4cb05215da4a4cccec409"
  },
  "user_id": {
    "$oid": "671b00000000000000000101"
  },
  "type": "like",
  "from_user": {
    "$oid": "671b00000000000000000107"
  },
  "post_id": {
    "$oid": "68e4c90c215da4a4cccec397"
  },
  "read": true,
  "created_at": {
    "$date": "2025-10-07T08:10:45.602Z"
  }
},
{
  "_id": {
    "$oid": "68e4cb05215da4a4cccec40a"
  },
  "user_id": {
    "$oid": "671b00000000000000000107"
  },
  "type": "mention",
  "from_user": {
    "$oid": "671b00000000000000000106"
  },
  "post_id": {
    "$oid": "68e4c90d215da4a4cccec39b"
  },
  "read": false,
  "created_at": {
    "$date": "2025-10-07T08:10:45.608Z"
  }
},
{
  "_id": {
    "$oid": "68e4cb05215da4a4cccec40b"
  },
  "user_id": {
    "$oid": "671b00000000000000000105"
  },
  "type": "like",
  "from_user": {
    "$oid": "671b00000000000000000102"
  },
  "post_id": {
    "$oid": "68e4c90c215da4a4cccec35f"
  },
  "read": false,
  "created_at": {
    "$date": "2025-10-07T08:10:45.616Z"
  }
},
{
  "_id": {
    "$oid": "68e4cb05215da4a4cccec40c"
  },
  "user_id": {
    "$oid": "671b00000000000000000104"
  },
  "type": "like",
  "from_user": {
    "$oid": "671b00000000000000000105"
  },
  "post_id": {
    "$oid": "68e4c90c215da4a4cccec366"
  },
  "read": true,
  "created_at": {
    "$date": "2025-10-07T08:10:45.623Z"
  }
},
{
  "_id": {
    "$oid": "68e4cb05215da4a4cccec40d"
  },
  "user_id": {
    "$oid": "671b00000000000000000105"
  },
  "type": "follow",
  "from_user": {
    "$oid": "671b00000000000000000101"
  },
  "post_id": null,
  "read": false,
  "created_at": {
    "$date": "2025-10-07T08:10:45.624Z"
  }
},
{
  "_id": {
    "$oid": "68e4cb05215da4a4cccec40e"
  },
  "user_id": {
    "$oid": "671b00000000000000000101"
  },
  "type": "mention",
  "from_user": {
    "$oid": "671b00000000000000000107"
  },
  "post_id": {
    "$oid": "68e4c90d215da4a4cccec3b0"
  },
  "read": false,
  "created_at": {
    "$date": "2025-10-07T08:10:45.630Z"
  }
},
{
  "_id": {
    "$oid": "68e4cb05215da4a4cccec40f"
  },
  "user_id": {
    "$oid": "671b00000000000000000101"
  },
  "type": "follow",
  "from_user": {
    "$oid": "671b00000000000000000103"
  },
  "post_id": null,
  "read": true,
  "created_at": {
    "$date": "2025-10-07T08:10:45.632Z"
  }
},
{
  "_id": {
    "$oid": "68e4cb05215da4a4cccec410"
  },
  "user_id": {
    "$oid": "671b00000000000000000101"
  },
  "type": "follow",
  "from_user": {
    "$oid": "671b00000000000000000104"
  },
  "post_id": null,
  "read": false,
  "created_at": {
    "$date": "2025-10-07T08:10:45.633Z"
  }
},
{
  "_id": {
    "$oid": "68e4cb05215da4a4cccec411"
  },
  "user_id": {
    "$oid": "671b00000000000000000102"
  },
  "type": "follow",
  "from_user": {
    "$oid": "671b00000000000000000106"
  },
  "post_id": null,
  "read": false,
  "created_at": {
    "$date": "2025-10-07T08:10:45.635Z"
  }
},
{
  "_id": {
    "$oid": "68e4cb05215da4a4cccec412"
  },
  "user_id": {
    "$oid": "671b00000000000000000107"
  },
  "type": "comment",
  "from_user": {
    "$oid": "671b00000000000000000101"
  },
  "post_id": {
    "$oid": "68e4c90d215da4a4cccec3bb"
  },
  "read": true,
  "created_at": {
    "$date": "2025-10-07T08:10:45.642Z"
  }
},
{
  "_id": {
    "$oid": "68e4cb05215da4a4cccec413"
  },
  "user_id": {
    "$oid": "671b00000000000000000108"
  },
  "type": "like",
  "from_user": {
    "$oid": "671b00000000000000000102"
  },
  "post_id": {
    "$oid": "68e4c90d215da4a4cccec3de"
  },
  "read": false,
  "created_at": {
    "$date": "2025-10-07T08:10:45.650Z"
  }
},
{
  "_id": {
    "$oid": "68e4cb05215da4a4cccec414"
  },
  "user_id": {
    "$oid": "671b00000000000000000105"
  },
  "type": "mention",
  "from_user": {
    "$oid": "671b00000000000000000104"
  },
  "post_id": {
    "$oid": "68e4c90d215da4a4cccec3b9"
  },
  "read": false,
  "created_at": {
    "$date": "2025-10-07T08:10:45.658Z"
  }
},
{
  "_id": {
    "$oid": "68e4cb05215da4a4cccec415"
  },
  "user_id": {
    "$oid": "671b00000000000000000103"
  },
  "type": "like",
  "from_user": {
    "$oid": "671b00000000000000000107"
  },
  "post_id": {
    "$oid": "68e4c90c215da4a4cccec355"
  },
  "read": false,
  "created_at": {
    "$date": "2025-10-07T08:10:45.664Z"
  }
},
{
  "_id": {
    "$oid": "68e4cb05215da4a4cccec416"
  },
  "user_id": {
    "$oid": "671b00000000000000000104"
  },
  "type": "follow",
  "from_user": {
    "$oid": "671b00000000000000000102"
  },
  "post_id": null,
  "read": false,
  "created_at": {
    "$date": "2025-10-07T08:10:45.665Z"
  }
},
{
  "_id": {
    "$oid": "68e4cb05215da4a4cccec417"
  },
  "user_id": {
    "$oid": "671b00000000000000000107"
  },
  "type": "mention",
  "from_user": {
    "$oid": "671b00000000000000000104"
  },
  "post_id": {
    "$oid": "68e4c90c215da4a4cccec354"
  },
  "read": true,
  "created_at": {
    "$date": "2025-10-07T08:10:45.672Z"
  }
},
{
  "_id": {
    "$oid": "68e4cb05215da4a4cccec418"
  },
  "user_id": {
    "$oid": "671b00000000000000000101"
  },
  "type": "comment",
  "from_user": {
    "$oid": "671b00000000000000000103"
  },
  "post_id": {
    "$oid": "68e4c90d215da4a4cccec3ac"
  },
  "read": false,
  "created_at": {
    "$date": "2025-10-07T08:10:45.682Z"
  }
},
{
  "_id": {
    "$oid": "68e4cb05215da4a4cccec419"
  },
  "user_id": {
    "$oid": "671b00000000000000000107"
  },
  "type": "mention",
  "from_user": {
    "$oid": "671b00000000000000000103"
  },
  "post_id": {
    "$oid": "68e4c90c215da4a4cccec391"
  },
  "read": true,
  "created_at": {
    "$date": "2025-10-07T08:10:45.689Z"
  }
},
{
  "_id": {
    "$oid": "68e4cb05215da4a4cccec41a"
  },
  "user_id": {
    "$oid": "671b00000000000000000106"
  },
  "type": "like",
  "from_user": {
    "$oid": "671b00000000000000000108"
  },
  "post_id": {
    "$oid": "68e4c90d215da4a4cccec3bf"
  },
  "read": true,
  "created_at": {
    "$date": "2025-10-07T08:10:45.695Z"
  }
},
{
  "_id": {
    "$oid": "68e4cb05215da4a4cccec41b"
  },
  "user_id": {
    "$oid": "671b00000000000000000107"
  },
  "type": "follow",
  "from_user": {
    "$oid": "671b00000000000000000105"
  },
  "post_id": null,
  "read": true,
  "created_at": {
    "$date": "2025-10-07T08:10:45.697Z"
  }
},
{
  "_id": {
    "$oid": "68e4cb05215da4a4cccec41c"
  },
  "user_id": {
    "$oid": "671b00000000000000000108"
  },
  "type": "follow",
  "from_user": {
    "$oid": "671b00000000000000000107"
  },
  "post_id": null,
  "read": false,
  "created_at": {
    "$date": "2025-10-07T08:10:45.699Z"
  }
},
{
  "_id": {
    "$oid": "68e4cb05215da4a4cccec41d"
  },
  "user_id": {
    "$oid": "671b00000000000000000108"
  },
  "type": "like",
  "from_user": {
    "$oid": "671b00000000000000000102"
  },
  "post_id": {
    "$oid": "68e4c90c215da4a4cccec38a"
  },
  "read": true,
  "created_at": {
    "$date": "2025-10-07T08:10:45.705Z"
  }
},
{
  "_id": {
    "$oid": "68e4cb05215da4a4cccec41e"
  },
  "user_id": {
    "$oid": "671b00000000000000000108"
  },
  "type": "comment",
  "from_user": {
    "$oid": "671b00000000000000000106"
  },
  "post_id": {
    "$oid": "68e4c90c215da4a4cccec352"
  },
  "read": false,
  "created_at": {
    "$date": "2025-10-07T08:10:45.713Z"
  }
},
{
  "_id": {
    "$oid": "68e4cb05215da4a4cccec41f"
  },
  "user_id": {
    "$oid": "671b00000000000000000103"
  },
  "type": "like",
  "from_user": {
    "$oid": "671b00000000000000000101"
  },
  "post_id": {
    "$oid": "68e4c90d215da4a4cccec3c1"
  },
  "read": true,
  "created_at": {
    "$date": "2025-10-07T08:10:45.720Z"
  }
},
{
  "_id": {
    "$oid": "68e4cb05215da4a4cccec420"
  },
  "user_id": {
    "$oid": "671b00000000000000000105"
  },
  "type": "comment",
  "from_user": {
    "$oid": "671b00000000000000000101"
  },
  "post_id": {
    "$oid": "68e4c90d215da4a4cccec3ba"
  },
  "read": false,
  "created_at": {
    "$date": "2025-10-07T08:10:45.727Z"
  }
},
{
  "_id": {
    "$oid": "68e4cb05215da4a4cccec421"
  },
  "user_id": {
    "$oid": "671b00000000000000000103"
  },
  "type": "mention",
  "from_user": {
    "$oid": "671b00000000000000000106"
  },
  "post_id": {
    "$oid": "68e4c90c215da4a4cccec36f"
  },
  "read": false,
  "created_at": {
    "$date": "2025-10-07T08:10:45.733Z"
  }
},
{
  "_id": {
    "$oid": "68e4cb05215da4a4cccec422"
  },
  "user_id": {
    "$oid": "671b00000000000000000107"
  },
  "type": "mention",
  "from_user": {
    "$oid": "671b00000000000000000108"
  },
  "post_id": {
    "$oid": "68e4c90c215da4a4cccec38c"
  },
  "read": false,
  "created_at": {
    "$date": "2025-10-07T08:10:45.741Z"
  }
},
{
  "_id": {
    "$oid": "68e4cb05215da4a4cccec423"
  },
  "user_id": {
    "$oid": "671b00000000000000000106"
  },
  "type": "comment",
  "from_user": {
    "$oid": "671b00000000000000000101"
  },
  "post_id": {
    "$oid": "68e4c90c215da4a4cccec395"
  },
  "read": false,
  "created_at": {
    "$date": "2025-10-07T08:10:45.747Z"
  }
},
{
  "_id": {
    "$oid": "68e4cb05215da4a4cccec424"
  },
  "user_id": {
    "$oid": "671b00000000000000000103"
  },
  "type": "like",
  "from_user": {
    "$oid": "671b00000000000000000102"
  },
  "post_id": {
    "$oid": "68e4c90c215da4a4cccec378"
  },
  "read": true,
  "created_at": {
    "$date": "2025-10-07T08:10:45.754Z"
  }
},
{
  "_id": {
    "$oid": "68e4cb05215da4a4cccec425"
  },
  "user_id": {
    "$oid": "671b00000000000000000108"
  },
  "type": "mention",
  "from_user": {
    "$oid": "671b00000000000000000107"
  },
  "post_id": {
    "$oid": "68e4c90d215da4a4cccec3ce"
  },
  "read": false,
  "created_at": {
    "$date": "2025-10-07T08:10:45.760Z"
  }
},
{
  "_id": {
    "$oid": "68e4cb05215da4a4cccec426"
  },
  "user_id": {
    "$oid": "671b00000000000000000105"
  },
  "type": "comment",
  "from_user": {
    "$oid": "671b00000000000000000106"
  },
  "post_id": {
    "$oid": "68e4c90c215da4a4cccec37c"
  },
  "read": true,
  "created_at": {
    "$date": "2025-10-07T08:10:45.768Z"
  }
},
{
  "_id": {
    "$oid": "68e4cb05215da4a4cccec427"
  },
  "user_id": {
    "$oid": "671b00000000000000000105"
  },
  "type": "like",
  "from_user": {
    "$oid": "671b00000000000000000108"
  },
  "post_id": {
    "$oid": "68e4c90c215da4a4cccec360"
  },
  "read": true,
  "created_at": {
    "$date": "2025-10-07T08:10:45.775Z"
  }
},
{
  "_id": {
    "$oid": "68e4cb05215da4a4cccec428"
  },
  "user_id": {
    "$oid": "671b00000000000000000106"
  },
  "type": "comment",
  "from_user": {
    "$oid": "671b00000000000000000107"
  },
  "post_id": {
    "$oid": "68e4c90c215da4a4cccec357"
  },
  "read": true,
  "created_at": {
    "$date": "2025-10-07T08:10:45.781Z"
  }
},
{
  "_id": {
    "$oid": "68e4cb05215da4a4cccec429"
  },
  "user_id": {
    "$oid": "671b00000000000000000106"
  },
  "type": "comment",
  "from_user": {
    "$oid": "671b00000000000000000108"
  },
  "post_id": {
    "$oid": "68e4c90d215da4a4cccec3d9"
  },
  "read": true,
  "created_at": {
    "$date": "2025-10-07T08:10:45.787Z"
  }
},
{
  "_id": {
    "$oid": "68e4cb05215da4a4cccec42a"
  },
  "user_id": {
    "$oid": "671b00000000000000000103"
  },
  "type": "comment",
  "from_user": {
    "$oid": "671b00000000000000000101"
  },
  "post_id": {
    "$oid": "68e4c90c215da4a4cccec371"
  },
  "read": true,
  "created_at": {
    "$date": "2025-10-07T08:10:45.794Z"
  }
},
{
  "_id": {
    "$oid": "68e4cb05215da4a4cccec42b"
  },
  "user_id": {
    "$oid": "671b00000000000000000108"
  },
  "type": "like",
  "from_user": {
    "$oid": "671b00000000000000000103"
  },
  "post_id": {
    "$oid": "68e4c90d215da4a4cccec3be"
  },
  "read": false,
  "created_at": {
    "$date": "2025-10-07T08:10:45.801Z"
  }
},
{
  "_id": {
    "$oid": "68e4cb05215da4a4cccec42c"
  },
  "user_id": {
    "$oid": "671b00000000000000000108"
  },
  "type": "like",
  "from_user": {
    "$oid": "671b00000000000000000104"
  },
  "post_id": {
    "$oid": "68e4c90c215da4a4cccec376"
  },
  "read": false,
  "created_at": {
    "$date": "2025-10-07T08:10:45.808Z"
  }
},
{
  "_id": {
    "$oid": "68e4cb05215da4a4cccec42d"
  },
  "user_id": {
    "$oid": "671b00000000000000000104"
  },
  "type": "mention",
  "from_user": {
    "$oid": "671b00000000000000000102"
  },
  "post_id": {
    "$oid": "68e4c90d215da4a4cccec3ae"
  },
  "read": false,
  "created_at": {
    "$date": "2025-10-07T08:10:45.813Z"
  }
},
{
  "_id": {
    "$oid": "68e4cb05215da4a4cccec42e"
  },
  "user_id": {
    "$oid": "671b00000000000000000105"
  },
  "type": "mention",
  "from_user": {
    "$oid": "671b00000000000000000104"
  },
  "post_id": {
    "$oid": "68e4c90c215da4a4cccec36a"
  },
  "read": false,
  "created_at": {
    "$date": "2025-10-07T08:10:45.823Z"
  }
},
{
  "_id": {
    "$oid": "68e4cb05215da4a4cccec42f"
  },
  "user_id": {
    "$oid": "671b00000000000000000104"
  },
  "type": "like",
  "from_user": {
    "$oid": "671b00000000000000000106"
  },
  "post_id": {
    "$oid": "68e4c90d215da4a4cccec3c9"
  },
  "read": true,
  "created_at": {
    "$date": "2025-10-07T08:10:45.835Z"
  }
},
{
  "_id": {
    "$oid": "68e4cb05215da4a4cccec430"
  },
  "user_id": {
    "$oid": "671b00000000000000000104"
  },
  "type": "follow",
  "from_user": {
    "$oid": "671b00000000000000000105"
  },
  "post_id": null,
  "read": false,
  "created_at": {
    "$date": "2025-10-07T08:10:45.843Z"
  }
},
{
  "_id": {
    "$oid": "68e4cb05215da4a4cccec431"
  },
  "user_id": {
    "$oid": "671b00000000000000000103"
  },
  "type": "follow",
  "from_user": {
    "$oid": "671b00000000000000000107"
  },
  "post_id": null,
  "read": true,
  "created_at": {
    "$date": "2025-10-07T08:10:45.845Z"
  }
},
{
  "_id": {
    "$oid": "68e4cb05215da4a4cccec432"
  },
  "user_id": {
    "$oid": "671b00000000000000000103"
  },
  "type": "comment",
  "from_user": {
    "$oid": "671b00000000000000000105"
  },
  "post_id": {
    "$oid": "68e4c90d215da4a4cccec3c4"
  },
  "read": true,
  "created_at": {
    "$date": "2025-10-07T08:10:45.851Z"
  }
},
{
  "_id": {
    "$oid": "68e4cb05215da4a4cccec433"
  },
  "user_id": {
    "$oid": "671b00000000000000000102"
  },
  "type": "follow",
  "from_user": {
    "$oid": "671b00000000000000000108"
  },
  "post_id": null,
  "read": false,
  "created_at": {
    "$date": "2025-10-07T08:10:45.853Z"
  }
},
{
  "_id": {
    "$oid": "68e4cb05215da4a4cccec434"
  },
  "user_id": {
    "$oid": "671b00000000000000000106"
  },
  "type": "like",
  "from_user": {
    "$oid": "671b00000000000000000108"
  },
  "post_id": {
    "$oid": "68e4c90d215da4a4cccec3ce"
  },
  "read": true,
  "created_at": {
    "$date": "2025-10-07T08:10:45.859Z"
  }
},
{
  "_id": {
    "$oid": "68e4cb05215da4a4cccec435"
  },
  "user_id": {
    "$oid": "671b00000000000000000106"
  },
  "type": "comment",
  "from_user": {
    "$oid": "671b00000000000000000105"
  },
  "post_id": {
    "$oid": "68e4c90c215da4a4cccec372"
  },
  "read": false,
  "created_at": {
    "$date": "2025-10-07T08:10:45.866Z"
  }
},
{
  "_id": {
    "$oid": "68e4cb05215da4a4cccec436"
  },
  "user_id": {
    "$oid": "671b00000000000000000101"
  },
  "type": "like",
  "from_user": {
    "$oid": "671b00000000000000000108"
  },
  "post_id": {
    "$oid": "68e4c90d215da4a4cccec3a8"
  },
  "read": true,
  "created_at": {
    "$date": "2025-10-07T08:10:45.873Z"
  }
},
{
  "_id": {
    "$oid": "68e4cb05215da4a4cccec437"
  },
  "user_id": {
    "$oid": "671b00000000000000000104"
  },
  "type": "like",
  "from_user": {
    "$oid": "671b00000000000000000103"
  },
  "post_id": {
    "$oid": "68e4c90d215da4a4cccec3bc"
  },
  "read": true,
  "created_at": {
    "$date": "2025-10-07T08:10:45.879Z"
  }
},
{
  "_id": {
    "$oid": "68e4cb05215da4a4cccec438"
  },
  "user_id": {
    "$oid": "671b00000000000000000103"
  },
  "type": "like",
  "from_user": {
    "$oid": "671b00000000000000000107"
  },
  "post_id": {
    "$oid": "68e4c90c215da4a4cccec36a"
  },
  "read": false,
  "created_at": {
    "$date": "2025-10-07T08:10:45.889Z"
  }
},
{
  "_id": {
    "$oid": "68e4cb05215da4a4cccec439"
  },
  "user_id": {
    "$oid": "671b00000000000000000103"
  },
  "type": "comment",
  "from_user": {
    "$oid": "671b00000000000000000107"
  },
  "post_id": {
    "$oid": "68e4c90c215da4a4cccec35e"
  },
  "read": false,
  "created_at": {
    "$date": "2025-10-07T08:10:45.899Z"
  }
},
{
  "_id": {
    "$oid": "68e4cb05215da4a4cccec43a"
  },
  "user_id": {
    "$oid": "671b00000000000000000101"
  },
  "type": "like",
  "from_user": {
    "$oid": "671b00000000000000000107"
  },
  "post_id": {
    "$oid": "68e4c90d215da4a4cccec39e"
  },
  "read": false,
  "created_at": {
    "$date": "2025-10-07T08:10:45.908Z"
  }
},
{
  "_id": {
    "$oid": "68e4cb05215da4a4cccec43b"
  },
  "user_id": {
    "$oid": "671b00000000000000000108"
  },
  "type": "comment",
  "from_user": {
    "$oid": "671b00000000000000000107"
  },
  "post_id": {
    "$oid": "68e4c90c215da4a4cccec36b"
  },
  "read": false,
  "created_at": {
    "$date": "2025-10-07T08:10:45.915Z"
  }
},
{
  "_id": {
    "$oid": "68e4cb05215da4a4cccec43c"
  },
  "user_id": {
    "$oid": "671b00000000000000000101"
  },
  "type": "follow",
  "from_user": {
    "$oid": "671b00000000000000000105"
  },
  "post_id": null,
  "read": false,
  "created_at": {
    "$date": "2025-10-07T08:10:45.920Z"
  }
},
{
  "_id": {
    "$oid": "68e4cb05215da4a4cccec43d"
  },
  "user_id": {
    "$oid": "671b00000000000000000108"
  },
  "type": "comment",
  "from_user": {
    "$oid": "671b00000000000000000106"
  },
  "post_id": {
    "$oid": "68e4c90d215da4a4cccec3c5"
  },
  "read": true,
  "created_at": {
    "$date": "2025-10-07T08:10:45.926Z"
  }
},
{
  "_id": {
    "$oid": "68e4cb05215da4a4cccec43e"
  },
  "user_id": {
    "$oid": "671b00000000000000000106"
  },
  "type": "mention",
  "from_user": {
    "$oid": "671b00000000000000000101"
  },
  "post_id": {
    "$oid": "68e4c90c215da4a4cccec34e"
  },
  "read": true,
  "created_at": {
    "$date": "2025-10-07T08:10:45.932Z"
  }
},
{
  "_id": {
    "$oid": "68e4cb05215da4a4cccec43f"
  },
  "user_id": {
    "$oid": "671b00000000000000000106"
  },
  "type": "like",
  "from_user": {
    "$oid": "671b00000000000000000102"
  },
  "post_id": {
    "$oid": "68e4c90d215da4a4cccec3c1"
  },
  "read": false,
  "created_at": {
    "$date": "2025-10-07T08:10:45.938Z"
  }
},
{
  "_id": {
    "$oid": "68e4cb05215da4a4cccec440"
  },
  "user_id": {
    "$oid": "671b00000000000000000101"
  },
  "type": "comment",
  "from_user": {
    "$oid": "671b00000000000000000105"
  },
  "post_id": {
    "$oid": "68e4c90d215da4a4cccec3a7"
  },
  "read": true,
  "created_at": {
    "$date": "2025-10-07T08:10:45.945Z"
  }
},
{
  "_id": {
    "$oid": "68e4cb05215da4a4cccec441"
  },
  "user_id": {
    "$oid": "671b00000000000000000103"
  },
  "type": "comment",
  "from_user": {
    "$oid": "671b00000000000000000108"
  },
  "post_id": {
    "$oid": "68e4c90c215da4a4cccec380"
  },
  "read": true,
  "created_at": {
    "$date": "2025-10-07T08:10:45.953Z"
  }
},
{
  "_id": {
    "$oid": "68e4cb05215da4a4cccec442"
  },
  "user_id": {
    "$oid": "671b00000000000000000107"
  },
  "type": "mention",
  "from_user": {
    "$oid": "671b00000000000000000106"
  },
  "post_id": {
    "$oid": "68e4c90c215da4a4cccec36e"
  },
  "read": true,
  "created_at": {
    "$date": "2025-10-07T08:10:45.960Z"
  }
},
{
  "_id": {
    "$oid": "68e4cb05215da4a4cccec443"
  },
  "user_id": {
    "$oid": "671b00000000000000000104"
  },
  "type": "like",
  "from_user": {
    "$oid": "671b00000000000000000105"
  },
  "post_id": {
    "$oid": "68e4c90d215da4a4cccec3c3"
  },
  "read": true,
  "created_at": {
    "$date": "2025-10-07T08:10:45.968Z"
  }
},
{
  "_id": {
    "$oid": "68e4cb05215da4a4cccec444"
  },
  "user_id": {
    "$oid": "671b00000000000000000107"
  },
  "type": "like",
  "from_user": {
    "$oid": "671b00000000000000000105"
  },
  "post_id": {
    "$oid": "68e4c90c215da4a4cccec376"
  },
  "read": false,
  "created_at": {
    "$date": "2025-10-07T08:10:45.975Z"
  }
},
{
  "_id": {
    "$oid": "68e4cb05215da4a4cccec445"
  },
  "user_id": {
    "$oid": "671b00000000000000000103"
  },
  "type": "like",
  "from_user": {
    "$oid": "671b00000000000000000104"
  },
  "post_id": {
    "$oid": "68e4c90d215da4a4cccec3a1"
  },
  "read": false,
  "created_at": {
    "$date": "2025-10-07T08:10:45.984Z"
  }
}]